archiver_client/__init__.py
archiver_client/archiver_client.py
archiver_client-1.0.0.dist-info/licenses/LICENSE
archiver_client-1.0.0.dist-info/WHEEL
archiver_client-1.0.0.dist-info/METADATA
archiver_client-1.0.0.dist-info/RECORD
