Metadata-Version: 2.4
Name: archiver_client
Version: 1.0.0
Summary: Pscheduler Result Archiver Client API
Author-email: Komal Thareja <kthare10@renci.org>
Requires-Python: >=3.8
License-File: LICENSE
Requires-Dist: requests
